vexa_client/__init__.py
vexa_client/test_funcs.py
vexa_client/vexa.py
vexa_client-0.5.4.dist-info/METADATA
vexa_client-0.5.4.dist-info/WHEEL
vexa_client-0.5.4.dist-info/top_level.txt
vexa_client-0.5.4.dist-info/RECORD
