Metadata-Version: 2.4
Name: vexa-client
Version: 0.5.4
Summary: Python client library for Vexa - privacy-first, open-source API for real-time meeting transcription
Home-page: https://github.com/Vexa-ai/vexa
Author: Vexa Team
Author-email: support@vexa.ai
License: MIT
Project-URL: Documentation, https://github.com/Vexa-ai/vexa/blob/main/docs/user_api_guide.md
Project-URL: Bug Tracker, https://github.com/Vexa-ai/vexa/issues
Project-URL: Discord, https://discord.com/invite/Ga9duGkVz9
Project-URL: Website, https://www.vexa.ai
Keywords: meeting transcription translation real-time api client vexa
Classifier: Development Status :: 4 - Beta
Classifier: Intended Audience :: Developers
Classifier: License :: OSI Approved :: MIT License
Classifier: Operating System :: OS Independent
Classifier: Programming Language :: Python :: 3
Classifier: Programming Language :: Python :: 3.7
Classifier: Programming Language :: Python :: 3.8
Classifier: Programming Language :: Python :: 3.9
Classifier: Programming Language :: Python :: 3.10
Classifier: Programming Language :: Python :: 3.11
Classifier: Programming Language :: Python :: 3.12
Classifier: Topic :: Software Development :: Libraries :: Python Modules
Classifier: Topic :: Communications :: Chat
Classifier: Topic :: Multimedia :: Sound/Audio :: Speech
Classifier: Topic :: Scientific/Engineering :: Artificial Intelligence
Requires-Python: >=3.7
Requires-Dist: requests>=2.25.0
Dynamic: author
Dynamic: author-email
Dynamic: classifier
Dynamic: description
Dynamic: description-content-type
Dynamic: home-page
Dynamic: keywords
Dynamic: license
Dynamic: project-url
Dynamic: requires-dist
Dynamic: requires-python
Dynamic: summary
